MANIFEST.in
README
README.rst
manifest_gen
setup.py
bin/manifest_gen
manifest_generator.egg-info/PKG-INFO
manifest_generator.egg-info/SOURCES.txt
manifest_generator.egg-info/dependency_links.txt
manifest_generator.egg-info/requires.txt
manifest_generator.egg-info/top_level.txt
manifestgen/__init__.py
manifestgen/app.py
manifestgen/args.py
manifestgen/md5digest.py
manifestgen/tests/__init__.py
manifestgen/tests/test_convert_filenames_to_urls.py
manifestgen/tests/test_parse_args.py