Metadata-Version: 1.1
Name: manifest-generator
Version: 1.0.0
Summary: A utility to smartly generate an HTML5 application cache manifest
Home-page: https://github.com/kdahlhaus/manifest_generator
Author: Kevin Dahlhausen
Author-email: kpd@powertwenty.com
License: GPL3
Keywords: html5 cache manifest
Platform: UNKNOWN
Classifier: Development Status :: 5 - Production/Stable
Classifier: Topic :: Internet :: WWW/HTTP
Classifier: License :: OSI Approved :: GNU General Public License v3 (GPLv3)
Classifier: Environment :: Console
